dirval/__init__.py
dirval/cli.py
dirval/core.py
dirval-1.1.4.dist-info/licenses/LICENSE
dirval-1.1.4.dist-info/METADATA
dirval-1.1.4.dist-info/WHEEL
dirval-1.1.4.dist-info/entry_points.txt
dirval-1.1.4.dist-info/top_level.txt
dirval-1.1.4.dist-info/RECORD
