Metadata-Version: 2.4
Name: dirval
Version: 1.1.4
Summary: Create and validate a directory stamp based on deterministic path hashing.
Author: Kevin Veen-Birkenbach
License: MIT License
Keywords: hash,directory,stamp,validation
Classifier: License :: OSI Approved :: MIT License
Classifier: Programming Language :: Python
Classifier: Programming Language :: Python :: 3
Requires-Python: >=3.9
License-File: LICENSE
Dynamic: license-file
